LICENSE
MANIFEST.in
README.rst
setup.cfg
setup.py
aws_with/__init__.py
aws_with/cli.py
aws_with/commands.py
aws_with/main.py
aws_with/monkey.py
aws_with/organizations.py
aws_with/output.py
aws_with/regions.py
aws_with/utils.py
aws_with/workplan.py
aws_with.egg-info/PKG-INFO
aws_with.egg-info/SOURCES.txt
aws_with.egg-info/dependency_links.txt
aws_with.egg-info/entry_points.txt
aws_with.egg-info/requires.txt
aws_with.egg-info/top_level.txt